src/UART_Rx.v
module uart_rx (
    input clk,
    input rst,
    input baud_tick,
    input rx,
    output reg [7:0] data
);
    
    // localparam CLOCK_FREQUENCY = 20000000;      // 20 MHz Clock
    // localparam BAUD_RATE = 9600;
    // localparam BAUD_DIVISION = (CLOCK_FREQUENCY / (16 * BAUD_RATE));
    
    // reg [7:0] baud_count = 0;
    // reg baud_tick = 0;

    // always @(posedge clk) begin
    //     if (rst) begin
    //         baud_count <= 0;
    //         baud_tick <= 0;
    //     end
    //     else begin
    //         if (baud_count == BAUD_DIVISION) begin
    //             baud_count <= 0;
    //             baud_tick <= 1;
    //         end
    //         else begin
    //             baud_count <= baud_count + 1;
    //             baud_tick <= 0;
    //         end
    //     end
    // end

    localparam IDLE = 4'b0000;
    localparam START = 4'b0001;
    localparam DATA_BIT_0 = 4'b0010;
    localparam DATA_BIT_1 = 4'b0011;
    localparam DATA_BIT_2 = 4'b0100;
    localparam DATA_BIT_3 = 4'b0101;
    localparam DATA_BIT_4 = 4'b0110;
    localparam DATA_BIT_5 = 4'b0111;
    localparam DATA_BIT_6 = 4'b1000;
    localparam DATA_BIT_7 = 4'b1001;
    localparam STOP = 4'b1010;

    reg [3:0] current_state, next_state;

    always @(posedge clk) begin
        if (rst) begin
            current_state <= IDLE;
            data <= 0;
        end
        else begin
            current_state <= next_state;
        end
    end

    reg [4:0] count_16 = 0;

    always @(*) begin
        case (current_state)
            IDLE: begin
                if (rx == 0) begin
                    next_state = START;
                end
            end
            START: begin
                if (baud_tick) begin
                    if (count_16 == 8) begin
                        count_16 = 0;
                        next_state = DATA_BIT_0;
                    end
                    else begin
                        count_16 = count_16 + 1;
                    end
                end
            end
            DATA_BIT_0: begin
                if (baud_tick) begin
                    if (count_16 == 16) begin
                        data[0] = rx;
                        count_16 = 0;
                        next_state = DATA_BIT_1;
                    end
                    else begin
                        count_16 = count_16 + 1;
                    end
                end
            end
            DATA_BIT_1: begin
                if (baud_tick) begin
                    if (count_16 == 16) begin
                        data[1] = rx;
                        count_16 = 0;
                        next_state = DATA_BIT_2;
                    end
                    else begin
                        count_16 = count_16 + 1;
                    end
                end
            end
            DATA_BIT_2: begin
                if (baud_tick) begin
                    if (count_16 == 16) begin
                        data[2] = rx;
                        count_16 = 0;
                        next_state = DATA_BIT_3;
                    end
                    else begin
                        count_16 = count_16 + 1;
                    end
                end
            end
            DATA_BIT_3: begin
                if (baud_tick) begin
                    if (count_16 == 16) begin
                        data[3] = rx;
                        count_16 = 0;
                        next_state = DATA_BIT_4;
                    end
                    else begin
                        count_16 = count_16 + 1;
                    end
                end
            end
            DATA_BIT_4: begin
                if (baud_tick) begin
                    if (count_16 == 16) begin
                        data[4] = rx;
                        count_16 = 0;
                        next_state = DATA_BIT_5;
                    end
                    else begin
                        count_16 = count_16 + 1;
                    end
                end
            end
            DATA_BIT_5: begin
                if (baud_tick) begin
                    if (count_16 == 16) begin
                        data[5] = rx;
                        count_16 = 0;
                        next_state = DATA_BIT_6;
                    end
                    else begin
                        count_16 = count_16 + 1;
                    end
                end
            end
            DATA_BIT_6: begin
                if (baud_tick) begin
                    if (count_16 == 16) begin
                        data[6] = rx;
                        count_16 = 0;
                        next_state = DATA_BIT_7;
                    end
                    else begin
                        count_16 = count_16 + 1;
                    end
                end
            end
            DATA_BIT_7: begin
                if (baud_tick) begin
                    if (count_16 == 16) begin
                        data[7] = rx;
                        count_16 = 0;
                        next_state = STOP;
                    end
                    else begin
                        count_16 = count_16 + 1;
                    end
                end
            end
            STOP: begin
                if (rx == 1) begin
                    next_state = IDLE;
                end
            end
            default: next_state = IDLE;
        endcase
    end

endmodule

tb/UART_Rx_tb.v
`timescale 1ns/1ns

module uart_rx_tb;
    
    reg clk,rst;
    reg baud_tick;
    reg rx;
    wire [7:0] data;

    uart_rx uut(clk,rst,baud_tick,rx,data);

    initial begin
        $dumpfile("./temp/UART_Rx_tb.vcd");
        $dumpvars(0,uart_rx_tb);
    end

    initial clk = 0;
    always #25 clk = ~clk;

    initial baud_tick = 0;
    always #3250 baud_tick = ~baud_tick;

    initial begin
        #50 rst = 1;
        #50 rst = 0;
        #104800 rx = 0;
        #104800 rx = 1;
        #104800 rx = 0;
        #104800 rx = 1;
        #104800 rx = 0;
        #104800 rx = 1;
        #104800 rx = 1;
        #104800 rx = 0;
        #104800 rx = 1;
        #104800 rx = 1;
        #104800 rx = 1;
        #200000 $finish;
    end

endmodule

temp/UART_Rx_tb.vcd
$date
	Thu Nov 30 21:00:08 2023
$end
$version
	Icarus Verilog
$end
$timescale
	1ns
$end
$scope module uart_rx_tb $end
$var wire 8 ! data [7:0] $end
$var reg 1 " baud_tick $end
$var reg 1 # clk $end
$var reg 1 $ rst $end
$var reg 1 % rx $end
$scope module uut $end
$var wire 1 " baud_tick $end
$var wire 1 # clk $end
$var wire 1 $ rst $end
$var wire 1 % rx $end
$var reg 5 & count_16 [4:0] $end
$var reg 4 ' current_state [3:0] $end
$var reg 8 ( data [7:0] $end
$var reg 4 ) next_state [3:0] $end
$upscope $end
$upscope $end
$enddefinitions $end
#0
$dumpvars
b0 )
bx (
bx '
b0 &
x%
x$
0#
0"
bx !
$end
#25
b0 '
1#
#50
0#
1$
#75
b0 !
b0 (
1#
#100
0#
0$
#125
1#
#150
0#
#175
1#
#200
0#
#225
1#
#250
0#
#275
1#
#300
0#
#325
1#
#350
0#
#375
1#
#400
0#
#425
1#
#450
0#
#475
1#
#500
0#
#525
1#
#550
0#
#575
1#
#600
0#
#625
1#
#650
0#
#675
1#
#700
0#
#725
1#
#750
0#
#775
1#
#800
0#
#825
1#
#850
0#
#875
1#
#900
0#
#925
1#
#950
0#
#975
1#
#1000
0#
#1025
1#
#1050
0#
#1075
1#
#1100
0#
#1125
1#
#1150
0#
#1175
1#
#1200
0#
#1225
1#
#1250
0#
#1275
1#
#1300
0#
#1325
1#
#1350
0#
#1375
1#
#1400
0#
#1425
1#
#1450
0#
#1475
1#
#1500
0#
#1525
1#
#1550
0#
#1575
1#
#1600
0#
#1625
1#
#1650
0#
#1675
1#
#1700
0#
#1725
1#
#1750
0#
#1775
1#
#1800
0#
#1825
1#
#1850
0#
#1875
1#
#1900
0#
#1925
1#
#1950
0#
#1975
1#
#2000
0#
#2025
1#
#2050
0#
#2075
1#
#2100
0#
#2125
1#
#2150
0#
#2175
1#
#2200
0#
#2225
1#
#2250
0#
#2275
1#
#2300
0#
#2325
1#
#2350
0#
#2375
1#
#2400
0#
#2425
1#
#2450
0#
#2475
1#
#2500
0#
#2525
1#
#2550
0#
#2575
1#
#2600
0#
#2625
1#
#2650
0#
#2675
1#
#2700
0#
#2725
1#
#2750
0#
#2775
1#
#2800
0#
#2825
1#
#2850
0#
#2875
1#
#2900
0#
#2925
1#
#2950
0#
#2975
1#
#3000
0#
#3025
1#
#3050
0#
#3075
1#
#3100
0#
#3125
1#
#3150
0#
#3175
1#
#3200
0#
#3225
1#
#3250
0#
1"
#3275
1#
#3300
0#
#3325
1#
#3350
0#
#3375
1#
#3400
0#
#3425
1#
#3450
0#
#3475
1#
#3500
0#
#3525
1#
#3550
0#
#3575
1#
#3600
0#
#3625
1#
#3650
0#
#3675
1#
#3700
0#
#3725
1#
#3750
0#
#3775
1#
#3800
0#
#3825
1#
#3850
0#
#3875
1#
#3900
0#
#3925
1#
#3950
0#
#3975
1#
#4000
0#
#4025
1#
#4050
0#
#4075
1#
#4100
0#
#4125
1#
#4150
0#
#4175
1#
#4200
0#
#4225
1#
#4250
0#
#4275
1#
#4300
0#
#4325
1#
#4350
0#
#4375
1#
#4400
0#
#4425
1#
#4450
0#
#4475
1#
#4500
0#
#4525
1#
#4550
0#
#4575
1#
#4600
0#
#4625
1#
#4650
0#
#4675
1#
#4700
0#
#4725
1#
#4750
0#
#4775
1#
#4800
0#
#4825
1#
#4850
0#
#4875
1#
#4900
0#
#4925
1#
#4950
0#
#4975
1#
#5000
0#
#5025
1#
#5050
0#
#5075
1#
#5100
0#
#5125
1#
#5150
0#
#5175
1#
#5200
0#
#5225
1#
#5250
0#
#5275
1#
#5300
0#
#5325
1#
#5350
0#
#5375
1#
#5400
0#
#5425
1#
#5450
0#
#5475
1#
#5500
0#
#5525
1#
#5550
0#
#5575
1#
#5600
0#
#5625
1#
#5650
0#
#5675
1#
#5700
0#
#5725
1#
#5750
0#
#5775
1#
#5800
0#
#5825
1#
#5850
0#
#5875
1#
#5900
0#
#5925
1#
#5950
0#
#5975
1#
#6000
0#
#6025
1#
#6050
0#
#6075
1#
#6100
0#
#6125
1#
#6150
0#
#6175
1#
#6200
0#
#6225
1#
#6250
0#
#6275
1#
#6300
0#
#6325
1#
#6350
0#
#6375
1#
#6400
0#
#6425
1#
#6450
0#
#6475
1#
#6500
0#
0"
#6525
1#
#6550
0#
#6575
1#
#6600
0#
#6625
1#
#6650
0#
#6675
1#
#6700
0#
#6725
1#
#6750
0#
#6775
1#
#6800
0#
#6825
1#
#6850
0#
#6875
1#
#6900
0#
#6925
1#
#6950
0#
#6975
1#
#7000
0#
#7025
1#
#7050
0#
#7075
1#
#7100
0#
#7125
1#
#7150
0#
#7175
1#
#7200
0#
#7225
1#
#7250
0#
#7275
1#
#7300
0#
#7325
1#
#7350
0#
#7375
1#
#7400
0#
#7425
1#
#7450
0#
#7475
1#
#7500
0#
#7525
1#
#7550
0#
#7575
1#
#7600
0#
#7625
1#
#7650
0#
#7675
1#
#7700
0#
#7725
1#
#7750
0#
#7775
1#
#7800
0#
#7825
1#
#7850
0#
#7875
1#
#7900
0#
#7925
1#
#7950
0#
#7975
1#
#8000
0#
#8025
1#
#8050
0#
#8075
1#
#8100
0#
#8125
1#
#8150
0#
#8175
1#
#8200
0#
#8225
1#
#8250
0#
#8275
1#
#8300
0#
#8325
1#
#8350
0#
#8375
1#
#8400
0#
#8425
1#
#8450
0#
#8475
1#
#8500
0#
#8525
1#
#8550
0#
#8575
1#
#8600
0#
#8625
1#
#8650
0#
#8675
1#
#8700
0#
#8725
1#
#8750
0#
#8775
1#
#8800
0#
#8825
1#
#8850
0#
#8875
1#
#8900
0#
#8925
1#
#8950
0#
#8975
1#
#9000
0#
#9025
1#
#9050
0#
#9075
1#
#9100
0#
#9125
1#
#9150
0#
#9175
1#
#9200
0#
#9225
1#
#9250
0#
#9275
1#
#9300
0#
#9325
1#
#9350
0#
#9375
1#
#9400
0#
#9425
1#
#9450
0#
#9475
1#
#9500
0#
#9525
1#
#9550
0#
#9575
1#
#9600
0#
#9625
1#
#9650
0#
#9675
1#
#9700
0#
#9725
1#
#9750
0#
1"
