src/UART_Rx.v
module uart_rx (
    input clk,
    input rst,
    input baud_tick,
    input rx,
    output reg [7:0] data
);
    
    // localparam CLOCK_FREQUENCY = 20000000;      // 20 MHz Clock
    // localparam BAUD_RATE = 9600;
    // localparam BAUD_DIVISION = (CLOCK_FREQUENCY / (16 * BAUD_RATE));
    
    // reg [7:0] baud_count = 0;
    // reg baud_tick = 0;

    // always @(posedge clk) begin
    //     if (rst) begin
    //         baud_count <= 0;
    //         baud_tick <= 0;
    //     end
    //     else begin
    //         if (baud_count == BAUD_DIVISION) begin
    //             baud_count <= 0;
    //             baud_tick <= 1;
    //         end
    //         else begin
    //             baud_count <= baud_count + 1;
    //             baud_tick <= 0;
    //         end
    //     end
    // end

    localparam IDLE = 4'b0000;
    localparam START = 4'b0001;
    localparam DATA_BIT_0 = 4'b0010;
    localparam DATA_BIT_1 = 4'b0011;
    localparam DATA_BIT_2 = 4'b0100;
    localparam DATA_BIT_3 = 4'b0101;
    localparam DATA_BIT_4 = 4'b0110;
    localparam DATA_BIT_5 = 4'b0111;
    localparam DATA_BIT_6 = 4'b1000;
    localparam DATA_BIT_7 = 4'b1001;
    localparam STOP = 4'b1010;

    reg [3:0] current_state, next_state;

    always @(posedge clk) begin
        if (rst) begin
            current_state <= IDLE;
            data <= 0;
        end
        else begin
            current_state <= next_state;
        end
    end

    reg [4:0] count_16 = 0;

    always @(*) begin
        case (current_state)
            IDLE: begin
                if (rx == 0) begin
                    next_state = START;
                end
            end
            START: begin
                if (baud_tick) begin
                    if (count_16 == 8) begin
                        count_16 = 0;
                        next_state = DATA_BIT_0;
                    end
                    else begin
                        count_16 = count_16 + 1;
                    end
                end
            end
            DATA_BIT_0: begin
                if (baud_tick) begin
                    if (count_16 == 16) begin
                        data[0] = rx;
                        count_16 = 0;
                        next_state = DATA_BIT_1;
                    end
                    else begin
                        count_16 = count_16 + 1;
                    end
                end
            end
            DATA_BIT_1: begin
                if (baud_tick) begin
                    if (count_16 == 16) begin
                        data[1] = rx;
                        count_16 = 0;
                        next_state = DATA_BIT_2;
                    end
                    else begin
                        count_16 = count_16 + 1;
                    end
                end
            end
            DATA_BIT_2: begin
                if (baud_tick) begin
                    if (count_16 == 16) begin
                        data[2] = rx;
                        count_16 = 0;
                        next_state = DATA_BIT_3;
                    end
                    else begin
                        count_16 = count_16 + 1;
                    end
                end
            end
            DATA_BIT_3: begin
                if (baud_tick) begin
                    if (count_16 == 16) begin
                        data[3] = rx;
                        count_16 = 0;
                        next_state = DATA_BIT_4;
                    end
                    else begin
                        count_16 = count_16 + 1;
                    end
                end
            end
            DATA_BIT_4: begin
                if (baud_tick) begin
                    if (count_16 == 16) begin
                        data[4] = rx;
                        count_16 = 0;
                        next_state = DATA_BIT_5;
                    end
                    else begin
                        count_16 = count_16 + 1;
                    end
                end
            end
            DATA_BIT_5: begin
                if (baud_tick) begin
                    if (count_16 == 16) begin
                        data[5] = rx;
                        count_16 = 0;
                        next_state = DATA_BIT_6;
                    end
                    else begin
                        count_16 = count_16 + 1;
                    end
                end
            end
            DATA_BIT_6: begin
                if (baud_tick) begin
                    if (count_16 == 16) begin
                        data[6] = rx;
                        count_16 = 0;
                        next_state = DATA_BIT_7;
                    end
                    else begin
                        count_16 = count_16 + 1;
                    end
                end
            end
            DATA_BIT_7: begin
                if (baud_tick) begin
                    if (count_16 == 16) begin
                        data[7] = rx;
                        count_16 = 0;
                        next_state = STOP;
                    end
                    else begin
                        count_16 = count_16 + 1;
                    end
                end
            end
            STOP: begin
                if (rx == 1) begin
                    next_state = IDLE;
                end
            end
            default: next_state = IDLE;
        endcase
    end

endmodule

src/UART_Tx.v
module uart_tx (
    input clk,
    input rst,
    input en,
    input baud_tick,
    input [7:0] data,
    output reg tx
);
    
    // localparam CLOCK_FREQUENCY = 20000000;      // 20 MHz Clock
    // localparam BAUD_RATE = 9600;
    // localparam BAUD_DIVISION = (CLOCK_FREQUENCY / (16 * BAUD_RATE));
    
    // reg [7:0] baud_count = 0;
    // reg baud_tick = 0;

    // always @(posedge clk) begin
    //     if (rst) begin
    //         baud_count <= 0;
    //         baud_tick <= 0;
    //     end
    //     else begin
    //         if (baud_count == BAUD_DIVISION) begin
    //             baud_count <= 0;
    //             baud_tick <= 1;
    //         end
    //         else begin
    //             baud_count <= baud_count + 1;
    //             baud_tick <= 0;
    //         end
    //     end
    // end

    localparam IDLE = 4'b0000;
    localparam START = 4'b0001;
    localparam DATA_BIT_0 = 4'b0010;
    localparam DATA_BIT_1 = 4'b0011;
    localparam DATA_BIT_2 = 4'b0100;
    localparam DATA_BIT_3 = 4'b0101;
    localparam DATA_BIT_4 = 4'b0110;
    localparam DATA_BIT_5 = 4'b0111;
    localparam DATA_BIT_6 = 4'b1000;
    localparam DATA_BIT_7 = 4'b1001;
    localparam STOP = 4'b1010;

    reg [3:0] current_state, next_state;

    always @(posedge clk) begin
        if (rst) begin
            current_state <= IDLE;
        end
        else begin
            current_state <= next_state;
        end
    end

    reg [5:0] count_16 = 0;

    always @(*) begin
        case (current_state)
            IDLE: begin
                tx = 1;
                if (en) begin
                    count_16 = 0;
                    next_state = START;
                end
            end
            START: begin
                if (baud_tick) begin
                    tx = 0;
                    if (count_16 == 16) begin
                        count_16 = 0;
                        next_state = DATA_BIT_0;
                    end
                    else begin
                        count_16 = count_16 + 1;
                    end
                end
            end
            DATA_BIT_0: begin
                if (baud_tick) begin
                    tx = data[0];
                    if (count_16 == 16) begin
                        count_16 = 0;
                        next_state = DATA_BIT_1;
                    end
                    else begin
                        count_16 = count_16 + 1;
                    end
                end
            end
            DATA_BIT_1: begin
                if (baud_tick) begin
                    tx = data[1];
                    if (count_16 == 16) begin
                        count_16 = 0;
                        next_state = DATA_BIT_2;
                    end
                    else begin
                        count_16 = count_16 + 1;
                    end
                end
            end
            DATA_BIT_2: begin
                if (baud_tick) begin
                    tx = data[2];
                    if (count_16 == 16) begin
                        count_16 = 0;
                        next_state = DATA_BIT_3;
                    end
                    else begin
                        count_16 = count_16 + 1;
                    end
                end
            end
            DATA_BIT_3: begin
                if (baud_tick) begin
                    tx = data[3];
                    if (count_16 == 16) begin
                        count_16 = 0;
                        next_state = DATA_BIT_4;
                    end
                    else begin
                        count_16 = count_16 + 1;
                    end
                end
            end
            DATA_BIT_4: begin
                if (baud_tick) begin
                    tx = data[4];
                    if (count_16 == 16) begin
                        count_16 = 0;
                        next_state = DATA_BIT_5;
                    end
                    else begin
                        count_16 = count_16 + 1;
                    end
                end
            end
            DATA_BIT_5: begin
                if (baud_tick) begin
                    tx = data[5];
                    if (count_16 == 16) begin
                        count_16 = 0;
                        next_state = DATA_BIT_6;
                    end
                    else begin
                        count_16 = count_16 + 1;
                    end
                end
            end
            DATA_BIT_6: begin
                if (baud_tick) begin
                    tx = data[6];
                    if (count_16 == 16) begin
                        count_16 = 0;
                        next_state = DATA_BIT_7;
                    end
                    else begin
                        count_16 = count_16 + 1;
                    end
                end
            end
            DATA_BIT_7: begin
                if (baud_tick) begin
                    tx = data[7];
                    if (count_16 == 16) begin
                        count_16 = 0;
                        next_state = STOP;
                    end
                    else begin
                        count_16 = count_16 + 1;
                    end
                end
            end
            STOP: begin
                if (baud_tick) begin
                    tx = 1;
                    if (count_16 == 16) begin
                        count_16 = 0;
                        next_state = IDLE;
                    end
                    else begin
                        count_16 = count_16 + 1;
                    end
                end
            end
            default: next_state = IDLE;
        endcase
    end

endmodule

src/UART_Baud_Rate.v
module uart_baud_rate (
    input clk,
    input rst,
    input [31:0] baud_division,
    output reg baud_tick
);
    
    reg [31:0] baud_count = 0;

    always @(posedge clk) begin
        if (rst) begin
            baud_count <= 0;
            baud_tick <= 0;
        end
        else begin
            if (baud_division != 0) begin
                if (baud_count == baud_division) begin
                    baud_count <= 0;
                    baud_tick <= 1;
                end
                else begin
                    baud_count <= baud_count + 1;
                    baud_tick <= 0;
                end
            end
            else begin
                baud_count <= 0;
                baud_tick <= 0;
            end
        end
    end

endmodule

src/UART.v
module uart_top_design (
    input clk,
    input rst,
    input [1:0] address,
    input write_enable,
    input [31:0] write_data,
    input read_enable,
    output reg [7:0] read_data,
    output tx,
    input rx
);

    // Register Interface

    localparam BAUD_RATE = 2'b00;
    localparam TX_ENABLE = 2'b01;
    localparam TX_DATA = 2'b10;
    localparam RX_DATA = 3'b11;

    reg [31:0] baud_division;
    reg enable;
    reg [7:0] data_out;
    wire [7:0] data_in;

    always @(posedge clk) begin
        if (rst) begin
            baud_division <= 0;
            enable <= 0;
            data_out <= 0;
            read_data <= 0;
        end
    end

    always @(*) begin
        case (address)
            BAUD_RATE: begin
                if (write_enable) begin
                    baud_division = write_data;
                end
            end
            TX_ENABLE: begin
                if (write_enable) begin
                    enable = write_data[0];
                end
            end
            TX_DATA: begin
                if (write_enable) begin
                    data_out = write_data[7:0];
                end
            end
            RX_DATA: begin
                if (read_enable) begin
                    read_data = data_in;
                end
            end
            // default: 
        endcase
    end

    // Baud Rate Interface

    wire baud_tick;
    
    uart_baud_rate uut_uart_baud_rate(
        .clk (clk),
        .rst (rst),
        .baud_division (baud_division),
        .baud_tick (baud_tick)
    );

    // Transmitter Interface

    uart_tx uut_uart_tx(
        .clk (clk),
        .rst (rst),
        .en (enable),
        .baud_tick (baud_tick),
        .data (data_out),
        .tx (tx)
    );

    // Receiver Interface

    uart_rx uut_uart_rx(
        .clk (clk),
        .rst (rst),
        .baud_tick (baud_tick),
        .rx (rx),
        .data (data_in)
    );
    
endmodule

tb/UART_Test_tb.v
`timescale 1ns/1ns

module uart_test_tb;
    
    reg clk;
    reg rst;
    reg [1:0] address;
    reg write_enable;
    reg [31:0] write_data;
    reg read_enable;
    wire [7:0] read_data;
    wire tx;
    reg rx;

    uart_top_design uut(clk,rst,address,write_enable,write_data,read_enable,read_data,tx,rx);

    initial begin
        $dumpfile("./temp/UART_Test_tb.vcd");
        $dumpvars(0,uart_test_tb);
    end

    initial clk = 0;
    always #25 clk = ~clk;

    initial begin
        rst = 1;
        #100 rst = 0;
        #100 address = 0;
        #100 write_data = 130;
        #100 write_enable = 1;
        #100 write_enable = 0;
        #100 address = 1;
        #100 write_data = 1;
        #100 write_enable = 1;
        #100 address = 2;
        #100 write_data = 8'b0110_1001;
        #100 address = 1;
        #100 write_data = 0;
        #100 write_enable = 1;
        #100 address = 3;
        #100 write_enable = 1;
        #100 write_data = 8'b1011_0100;
        #115350 rx = 0;
        #115350 rx = 0;
        #115350 rx = 1;
        #115350 rx = 0;
        #115350 rx = 1;
        #115350 rx = 1;
        #115350 rx = 0;
        #115350 rx = 1;
        #1000000 read_enable = 1;
        #1000000 $finish;
    end

endmodule

temp/UART_Test_tb.vcd
$date
	Thu Nov 30 20:46:53 2023
$end
$version
	Icarus Verilog
$end
$timescale
	1ns
$end
$scope module uart_test_tb $end
$var wire 1 ! tx $end
$var wire 8 " read_data [7:0] $end
$var reg 2 # address [1:0] $end
$var reg 1 $ clk $end
$var reg 1 % read_enable $end
$var reg 1 & rst $end
$var reg 1 ' rx $end
$var reg 32 ( write_data [31:0] $end
$var reg 1 ) write_enable $end
$scope module uut $end
$var wire 2 * address [1:0] $end
$var wire 1 $ clk $end
$var wire 1 % read_enable $end
$var wire 1 & rst $end
$var wire 1 ' rx $end
$var wire 32 + write_data [31:0] $end
$var wire 1 ) write_enable $end
$var wire 1 ! tx $end
$var wire 8 , data_in [7:0] $end
$var wire 1 - baud_tick $end
$var reg 32 . baud_division [31:0] $end
$var reg 8 / data_out [7:0] $end
$var reg 1 0 enable $end
$var reg 8 1 read_data [7:0] $end
$scope module uut_uart_baud_rate $end
$var wire 32 2 baud_division [31:0] $end
$var wire 1 $ clk $end
$var wire 1 & rst $end
$var reg 32 3 baud_count [31:0] $end
$var reg 1 - baud_tick $end
$upscope $end
$scope module uut_uart_rx $end
$var wire 1 - baud_tick $end
$var wire 1 $ clk $end
$var wire 1 & rst $end
$var wire 1 ' rx $end
$var reg 5 4 count_16 [4:0] $end
$var reg 4 5 current_state [3:0] $end
$var reg 8 6 data [7:0] $end
$var reg 4 7 next_state [3:0] $end
$upscope $end
$scope module uut_uart_tx $end
$var wire 1 - baud_tick $end
$var wire 1 $ clk $end
$var wire 8 8 data [7:0] $end
$var wire 1 0 en $end
$var wire 1 & rst $end
$var reg 6 9 count_16 [5:0] $end
$var reg 4 : current_state [3:0] $end
$var reg 4 ; next_state [3:0] $end
$var reg 1 ! tx $end
$upscope $end
$upscope $end
$upscope $end
$enddefinitions $end
#0
$dumpvars
b0 ;
bx :
b0 9
bx 8
b0 7
bx 6
bx 5
b0 4
b0 3
bx 2
bx 1
x0
bx /
bx .
x-
bx ,
bx +
bx *
x)
bx (
x'
1&
x%
0$
bx #
bx "
x!
$end
#25
1!
0-
b0 :
b0 ,
b0 6
b0 5
b0 "
b0 1
b0 /
b0 8
00
b0 .
b0 2
1$
#50
0$
#75
1$
#100
0$
0&
#125
1$
#150
0$
#175
1$
#200
0$
b0 #
b0 *
#225
1$
#250
0$
#275
1$
#300
0$
b10000010 (
b10000010 +
#325
1$
#350
0$
#375
1$
#400
b10000010 .
b10000010 2
0$
1)
#425
b1 3
1$
#450
0$
#475
b10 3
1$
#500
0$
0)
#525
b11 3
1$
#550
0$
#575
b100 3
1$
#600
0$
b1 #
b1 *
#625
b101 3
1$
#650
0$
#675
b110 3
1$
#700
0$
b1 (
b1 +
#725
b111 3
1$
#750
0$
#775
b1000 3
1$
#800
b1 ;
10
0$
1)
#825
b1001 3
b1 :
1$
#850
0$
#875
b1010 3
1$
#900
b1 /
b1 8
0$
b10 #
b10 *
#925
b1011 3
1$
#950
0$
#975
b1100 3
1$
#1000
b1101001 /
b1101001 8
0$
b1101001 (
b1101001 +
#1025
b1101 3
1$
#1050
0$
#1075
b1110 3
1$
#1100
0$
b1 #
b1 *
#1125
b1111 3
1$
#1150
0$
#1175
b10000 3
1$
#1200
00
0$
b0 (
b0 +
#1225
b10001 3
1$
#1250
0$
#1275
b10010 3
1$
#1300
0$
#1325
b10011 3
1$
#1350
0$
#1375
b10100 3
1$
#1400
0$
b11 #
b11 *
#1425
b10101 3
1$
#1450
0$
#1475
b10110 3
1$
#1500
0$
#1525
b10111 3
1$
#1550
0$
#1575
b11000 3
1$
#1600
0$
b10110100 (
b10110100 +
#1625
b11001 3
1$
#1650
0$
#1675
b11010 3
1$
#1700
0$
#1725
b11011 3
1$
#1750
0$
#1775
b11100 3
1$
#1800
0$
#1825
b11101 3
1$
#1850
0$
#1875
b11110 3
1$
#1900
0$
#1925
b11111 3
1$
#1950
0$
#1975
b100000 3
1$
#2000
0$
#2025
b100001 3
1$
#2050
0$
#2075
b100010 3
1$
#2100
0$
#2125
b100011 3
1$
#2150
0$
#2175
b100100 3
1$
#2200
0$
#2225
b100101 3
1$
#2250
0$
#2275
b100110 3
1$
#2300
0$
#2325
b100111 3
1$
#2350
0$
#2375
b101000 3
1$
#2400
0$
#2425
b101001 3
1$
#2450
0$
#2475
b101010 3
1$
#2500
0$
#2525
b101011 3
1$
#2550
0$
#2575
b101100 3
1$
#2600
0$
#2625
b101101 3
1$
#2650
0$
#2675
b101110 3
1$
#2700
0$
#2725
b101111 3
1$
#2750
0$
#2775
b110000 3
1$
#2800
0$
#2825
b110001 3
1$
#2850
0$
#2875
b110010 3
1$
#2900
0$
#2925
b110011 3
1$
#2950
0$
#2975
b110100 3
1$
#3000
0$
#3025
b110101 3
1$
#3050
0$
#3075
b110110 3
1$
#3100
0$
#3125
b110111 3
1$
#3150
0$
#3175
b111000 3
1$
#3200
0$
#3225
b111001 3
1$
#3250
0$
#3275
b111010 3
1$
#3300
0$
#3325
b111011 3
1$
#3350
0$
#3375
b111100 3
1$
#3400
0$
#3425
b111101 3
1$
#3450
0$
#3475
b111110 3
1$
#3500
0$
#3525
b111111 3
1$
#3550
0$
#3575
b1000000 3
1$
#3600
0$
#3625
b1000001 3
1$
#3650
0$
#3675
b1000010 3
1$
#3700
0$
#3725
b1000011 3
1$
#3750
0$
#3775
b1000100 3
1$
#3800
0$
#3825
b1000101 3
1$
#3850
0$
#3875
b1000110 3
1$
#3900
0$
#3925
b1000111 3
1$
#3950
0$
#3975
b1001000 3
1$
#4000
0$
#4025
b1001001 3
1$
#4050
0$
#4075
b1001010 3
1$
#4100
0$
#4125
b1001011 3
1$
#4150
0$
#4175
b1001100 3
1$
#4200
0$
#4225
b1001101 3
1$
#4250
0$
#4275
b1001110 3
1$
#4300
0$
#4325
b1001111 3
1$
#4350
0$
#4375
b1010000 3
1$
#4400
0$
#4425
b1010001 3
1$
#4450
0$
#4475
b1010010 3
1$
#4500
0$
#4525
b1010011 3
1$
#4550
0$
#4575
b1010100 3
1$
#4600
0$
#4625
b1010101 3
1$
#4650
0$
#4675
b1010110 3
1$
#4700
0$
#4725
b1010111 3
1$
#4750
0$
#4775
b1011000 3
1$
#4800
0$
#4825
b1011001 3
1$
#4850
0$
#4875
b1011010 3
1$
#4900
0$
#4925
b1011011 3
1$
#4950
0$
#4975
b1011100 3
1$
#5000
0$
#5025
b1011101 3
1$
#5050
0$
#5075
b1011110 3
1$
#5100
0$
#5125
b1011111 3
1$
#5150
0$
#5175
b1100000 3
1$
#5200
0$
#5225
b1100001 3
1$
#5250
0$
#5275
b1100010 3
1$
#5300
0$
#5325
b1100011 3
1$
#5350
0$
#5375
b1100100 3
1$
#5400
0$
#5425
b1100101 3
1$
#5450
0$
#5475
b1100110 3
1$
#5500
0$
#5525
b1100111 3
1$
#5550
0$
#5575
b1101000 3
1$
#5600
0$
#5625
b1101001 3
1$
#5650
0$
#5675
b1101010 3
1$
#5700
0$
#5725
b1101011 3
1$
#5750
0$
#5775
b1101100 3
1$
#5800
0$
#5825
b1101101 3
1$
#5850
0$
#5875
b1101110 3
1$
#5900
0$
#5925
b1101111 3
1$
#5950
0$
#5975
b1110000 3
1$
#6000
0$
#6025
b1110001 3
1$
#6050
0$
#6075
b1110010 3
1$
#6100
0$
#6125
b1110011 3
1$
#6150
0$
#6175
b1110100 3
1$
#6200
0$
#6225
b1110101 3
1$
#6250
0$
#6275
b1110110 3
1$
#6300
0$
#6325
b1110111 3
1$
#6350
0$
#6375
b1111000 3
1$
#6400
0$
#6425
b1111001 3
1$
#6450
0$
#6475
b1111010 3
1$
#6500
0$
#6525
b1111011 3
1$
#6550
0$
#6575
b1111100 3
1$
#6600
0$
#6625
b1111101 3
1$
#6650
0$
#6675
b1111110 3
1$
#6700
0$
#6725
b1111111 3
1$
#6750
0$
#6775
b10000000 3
1$
#6800
0$
#6825
b10000001 3
1$
#6850
0$
#6875
b10000010 3
1$
#6900
0$
#6925
b1 9
0!
1-
b0 3
1$
#6950
0$
#6975
0-
b1 3
1$
#7000
0$
#7025
b10 3
1$
#7050
0$
#7075
b11 3
1$
#7100
0$
#7125
b100 3
1$
#7150
0$
#7175
b101 3
1$
#7200
0$
#7225
b110 3
1$
#7250
0$
#7275
b111 3
1$
#7300
0$
#7325
b1000 3
1$
#7350
0$
#7375
b1001 3
1$
#7400
0$
#7425
b1010 3
1$
#7450
0$
#7475
b1011 3
1$
#7500
0$
#7525
b1100 3
1$
#7550
0$
#7575
b1101 3
1$
#7600
0$
#7625
b1110 3
1$
#7650
0$
#7675
b1111 3
1$
#7700
0$
#7725
b10000 3
1$
#7750
0$
#7775
b10001 3
1$
#7800
0$
#7825
b10010 3
1$
#7850
0$
#7875
b10011 3
1$
#7900
0$
#7925
b10100 3
1$
#7950
0$
#7975
b10101 3
1$
#8000
0$
#8025
b10110 3
1$
#8050
0$
#8075
b10111 3
1$
#8100
0$
#8125
b11000 3
1$
#8150
0$
#8175
b11001 3
1$
#8200
0$
#8225
b11010 3
1$
#8250
0$
#8275
b11011 3
1$
#8300
0$
#8325
b11100 3
1$
#8350
0$
#8375
b11101 3
1$
#8400
0$
#8425
b11110 3
1$
#8450
0$
#8475
b11111 3
1$
#8500
0$
#8525
b100000 3
1$
#8550
0$
#8575
b100001 3
1$
#8600
0$
#8625
b100010 3
1$
#8650
0$
#8675
b100011 3
1$
#8700
0$
#8725
b100100 3
1$
#8750
0$
#8775
b100101 3
1$
#8800
0$
#8825
b100110 3
1$
#8850
0$
#8875
b100111 3
1$
#8900
0$
#8925
b101000 3
1$
#8950
0$
#8975
b101001 3
1$
#9000
0$
#9025
b101010 3
1$
#9050
0$
#9075
b101011 3
1$
#9100
0$
#9125
b101100 3
1$
#9150
0$
#9175
b101101 3
1$
#9200
0$
#9225
b101110 3
1$
#9250
0$
#9275
b101111 3
1$
#9300
0$
#9325
b110000 3
1$
#9350
0$
#9375
b110001 3
1$
#9400
0$
#9425
b110010 3
1$
#9450
0$
#9475
b110011 3
1$
#9500
0$
#9525
b110100 3
1$
#9550
0$
#9575
b110101 3
1$
#9600
0$
#9625
b110110 3
1$
#9650
0$
#9675
b110111 3
1$
#9700
0$
#9725
b111000 3
1$
#9750
0$
#9775
b111001 3
1$
#9800
0$
#9825
b111010 3
1$
#9850
0$
#9875
b111011 3
1$
#9900
0$
#9925
b111100 3
1$
#9950
0$
#9975
b111101 3
1$
#10000
0$
#10025
b111110 3
1$
#10050
0$
#10075
b111111 3
1$
#10100
0$
#10125
b1000000 3
1$
#10150
0$
#10175
b1000001 3
1$
#10200
0$
#10225
b1000010 3
1$
#10250
0$
#10275
b1000011 3
1$
#10300
0$
#10325
b1000100 3
1$
#10350
0$
#10375
b1000101 3
1$
#10400
0$
#10425
b1000110 3
1$
#10450
0$
#10475
b1000111 3
1$
#10500
0$
#10525
b1001000 3
1$
#10550
0$
#10575
b1001001 3
1$
#10600
0$
#10625
b1001010 3
1$
#10650
0$
#10675
b1001011 3
1$
#10700
0$
#10725
b1001100 3
1$
#10750
0$
#10775
b1001101 3
1$
#10800
0$
#10825
b1001110 3
1$
#10850
0$
#10875
b1001111 3
1$
#10900
0$
#10925
b1010000 3
1$
#10950
0$
#10975
b1010001 3
1$
#11000
0$
#11025
b1010010 3
1$
#11050
0$
#11075
b1010011 3
1$
#11100
0$
#11125
b1010100 3
1$
#11150
0$
#11175
b1010101 3
1$
#11200
0$
#11225
b1010110 3
1$
#11250
0$
#11275
b1010111 3
1$
#11300
0$
#11325
b1011000 3
1$
#11350
0$
#11375
b1011001 3
1$
#11400
0$
#11425
b1011010 3
1$
#11450
0$
#11475
b1011011 3
1$
#11500
0$
#11525
b1011100 3
1$
#11550
0$
#11575
b1011101 3
1$
#11600
0$
#11625
b1011110 3
1$
#11650
0$
#11675
b1011111 3
1$
#11700
0$
#11725
b1100000 3
1$
#11750
0$
#11775
b1100001 3
1$
#11800
0$
#11825
b1100010 3
1$
#11850
0$
#11875
b1100011 3
1$
#11900
0$
#11925
b1100100 3
1$
#11950
0$
#11975
b1100101 3
1$
#12000
0$
#12025
b1100110 3
1$
#12050
0$
#12075
b1100111 3
1$
#12100
0$
#12125
b1101000 3
1$
#12150
0$
#12175
b1101001 3
1$
#12200
0$
#12225
b1101010 3
1$
#12250
0$
#12275
b1101011 3
1$
#12300
0$
#12325
b1101100 3
1$
#12350
0$
#12375
b1101101 3
1$
#12400
0$
#12425
b1101110 3
1$
#12450
0$
#12475
b1101111 3
1$
#12500
0$
#12525
b1110000 3
1$
#12550
0$
#12575
b1110001 3
1$
#12600
0$
#12625
b1110010 3
1$
#12650
0$
#12675
b1110011 3
1$
#12700
0$
#12725
b1110100 3
1$
#12750
0$
#12775
b1110101 3
1$
#12800
0$
#12825
b1110110 3
1$
#12850
0$
#12875
b1110111 3
1$
#12900
0$
#12925
b1111000 3
1$
#12950
0$
#12975
b1111001 3
1$
#13000
0$
#13025
b1111010 3
1$
#13050
0$
#13075
b1111011 3
1$
#13100
0$
#13125
b1111100 3
1$
#13150
0$
#13175
b1111101 3
1$
#13200
0$
#13225
b1111110 3
1$
#13250
0$
#13275
b1111111 3
1$
#13300
0$
#13325
b10000000 3
1$
#13350
0$
#13375
b10000001 3
1$
#13400
0$
#13425
b10000010 3
1$
#13450
0$
#13475
b10 9
1-
b0 3
1$
#13500
0$
#13525
0-
b1 3
1$
#13550
0$
#13575
b10 3
1$
#13600
0$
#13625
b11 3
1$
#13650
0$
#13675
b100 3
1$
#13700
0$
#13725
b101 3
1$
#13750
0$
#13775
b110 3
1$
#13800
0$
#13825
b111 3
1$
#13850
0$
#13875
b1000 3
1$
#13900
0$
#13925
b1001 3
1$
#13950
0$
#13975
b1010 3
1$
#14000
0$
#14025
b1011 3
1$
#14050
0$
#14075
b1100 3
1$
#14100
0$
#14125
b1101 3
1$
#14150
0$
#14175
b1110 3
1$
#14200
0$
#14225
b1111 3
1$
#14250
0$
#14275
b10000 3
1$
#14300
0$
#14325
b10001 3
1$
#14350
0$
#14375
b10010 3
1$
#14400
0$
#14425
b10011 3
1$
#14450
0$
#14475
b10100 3
1$
#14500
0$
#14525
b10101 3
1$
#14550
0$
#14575
b10110 3
1$
#14600
0$
#14625
b10111 3
1$
#14650
0$
#14675
b11000 3
1$
#14700
0$
#14725
b11001 3
1$
#14750
0$
#14775
b11010 3
1$
#14800
0$
#14825
b11011 3
1$
#14850
0$
#14875
b11100 3
1$
#14900
0$
#14925
b11101 3
1$
#14950
0$
#14975
b11110 3
1$
#15000
0$
#15025
b11111 3
1$
#15050
0$
#15075
b100000 3
1$
#15100
0$
#15125
b100001 3
1$
#15150
0$
#15175
b100010 3
1$
#15200
0$
#15225
b100011 3
1$
#15250
0$
#15275
b100100 3
1$
#15300
0$
#15325
b100101 3
1$
#15350
0$
#15375
b100110 3
1$
#15400
0$
#15425
b100111 3
1$
#15450
0$
#15475
b101000 3
1$
#15500
0$
#15525
b101001 3
1$
#15550
0$
#15575
b101010 3
1$
#15600
0$
#15625
b101011 3
1$
#15650
0$
#15675
b101100 3
1$
#15700
0$
#15725
b101101 3
1$
#15750
0$
#15775
b101110 3
1$
#15800
0$
#15825
b101111 3
1$
#15850
0$
#15875
b110000 3
1$
#15900
0$
#15925
b110001 3
1$
#15950
0$
#15975
b110010 3
1$
#16000
0$
#16025
b110011 3
1$
#16050
0$
#16075
b110100 3
1$
#16100
0$
#16125
b110101 3
1$
#16150
0$
#16175
b110110 3
1$
#16200
0$
#16225
b110111 3
1$
#16250
0$
#16275
b111000 3
1$
#16300
0$
#16325
b111001 3
1$
#16350
0$
#16375
b111010 3
1$
#16400
0$
#16425
b111011 3
1$
#16450
0$
#16475
b111100 3
1$
#16500
0$
#16525
b111101 3
1$
#16550
0$
#16575
b111110 3
1$
#16600
0$
#16625
b111111 3
1$
#16650
0$
#16675
b1000000 3
1$
#16700
0$
#16725
b1000001 3
1$
#16750
0$
#16775
b1000010 3
1$
#16800
0$
#16825
b1000011 3
1$
#16850
0$
#16875
b1000100 3
1$
#16900
0$
#16925
b1000101 3
1$
#16950
0$
#16975
b1000110 3
1$
#17000
0$
#17025
b1000111 3
1$
#17050
0$
#17075
b1001000 3
1$
#17100
0$
#17125
b1001001 3
1$
#17150
0$
#17175
b1001010 3
1$
#17200
0$
#17225
b1001011 3
1$
#17250
0$
#17275
b1001100 3
1$
#17300
0$
#17325
b1001101 3
1$
#17350
0$
#17375
b1001110 3
1$
#17400
0$
#17425
b1001111 3
1$
#17450
0$
#17475
b1010000 3
1$
#17500
0$
#17525
b1010001 3
1$
#17550
0$
#17575
b1010010 3
1$
#17600
0$
#17625
b1010011 3
1$
#17650
0$
#17675
b1010100 3
1$
#17700
0$
#17725
b1010101 3
1$
#17750
0$
#17775
b1010110 3
1$
#17800
0$
#17825
b1010111 3
1$
#17850
0$
#17875
b1011000 3
1$
#17900
0$
#17925
b1011001 3
1$
#17950
0$
#17975
b1011010 3
1$
#18000
0$
#18025
b1011011 3
1$
#18050
0$
#18075
b1011100 3
1$
#18100
0$
#18125
b1011101 3
1$
#18150
0$
#18175
b1011110 3
1$
#18200
0$
#18225
b1011111 3
1$
#18250
0$
#18275
b1100000 3
1$
#18300
0$
#18325
b1100001 3
1$
#18350
0$
#18375
b1100010 3
1$
#18400
0$
#18425
b1100011 3
1$
#18450
0$
#18475
b1100100 3
1$
#18500
0$
#18525
b1100101 3
1$
#18550
0$
#18575
b1100110 3
1$
#18600
0$
#18625
b1100111 3
1$
#18650
0$
#18675
b1101000 3
1$
#18700
0$
#18725
b1101001 3
1$
#18750
0$
#18775
b1101010 3
1$
#18800
0$
#18825
b1101011 3
1$
#18850
0$
#18875
b1101100 3
1$
#18900
0$
#18925
b1101101 3
1$
#18950
0$
#18975
b1101110 3
1$
#19000
0$
#19025
b1101111 3
1$
#19050
0$
#19075
b1110000 3
1$
#19100
0$
#19125
b1110001 3
1$
#19150
0$
#19175
b1110010 3
1$
#19200
0$
#19225
b1110011 3
1$
#19250
0$
#19275
b1110100 3
1$
#19300
0$
#19325
b1110101 3
1$
#19350
0$
#19375
b1110110 3
1$
#19400
0$
#19425
b1110111 3
1$
#19450
0$
#19475
b1111000 3
1$
#19500
0$
#19525
b1111001 3
1$
#19550
0$
#19575
b1111010 3
1$
#19600
0$
#19625
b1111011 3
1$
#19650
0$
#19675
b1111100 3
1$
#19700
0$
#19725
b1111101 3
1$
#19750
0$
#19775
b1111110 3
1$
#19800
0$
#19825
b1111111 3
1$
#19850
0$
#19875
b10000000 3
1$
#19900
0$
#19925
b10000001 3
1$
#19950
0$
#19975
b10000010 3
1$
#20000
0$
#20025
b11 9
1-
b0 3
1$
#20050
0$
#20075
0-
b1 3
1$
#20100
0$
#20125
b10 3
1$
#20150
0$
#20175
b11 3
1$
#20200
0$
#20225
b100 3
1$
#20250
0$
#20275
b101 3
1$
#20300
0$
#20325
b110 3
1$
#20350
0$
#20375
b111 3
1$
#20400
0$
#20425
b1000 3
1$
#20450
0$
#20475
b1001 3
1$
#20500
0$
#20525
b1010 3
1$
#20550
0$
