src/UART_Tx.v
module uart_tx (
    input clk,
    input rst,
    input en,
    input baud_tick,
    input [7:0] data,
    output reg tx
);
    
    // localparam CLOCK_FREQUENCY = 20000000;      // 20 MHz Clock
    // localparam BAUD_RATE = 9600;
    // localparam BAUD_DIVISION = (CLOCK_FREQUENCY / (16 * BAUD_RATE));
    
    // reg [7:0] baud_count = 0;
    // reg baud_tick = 0;

    // always @(posedge clk) begin
    //     if (rst) begin
    //         baud_count <= 0;
    //         baud_tick <= 0;
    //     end
    //     else begin
    //         if (baud_count == BAUD_DIVISION) begin
    //             baud_count <= 0;
    //             baud_tick <= 1;
    //         end
    //         else begin
    //             baud_count <= baud_count + 1;
    //             baud_tick <= 0;
    //         end
    //     end
    // end

    localparam IDLE = 4'b0000;
    localparam START = 4'b0001;
    localparam DATA_BIT_0 = 4'b0010;
    localparam DATA_BIT_1 = 4'b0011;
    localparam DATA_BIT_2 = 4'b0100;
    localparam DATA_BIT_3 = 4'b0101;
    localparam DATA_BIT_4 = 4'b0110;
    localparam DATA_BIT_5 = 4'b0111;
    localparam DATA_BIT_6 = 4'b1000;
    localparam DATA_BIT_7 = 4'b1001;
    localparam STOP = 4'b1010;

    reg [3:0] current_state, next_state;

    always @(posedge clk) begin
        if (rst) begin
            current_state <= IDLE;
        end
        else begin
            current_state <= next_state;
        end
    end

    reg [5:0] count_16 = 0;

    always @(*) begin
        case (current_state)
            IDLE: begin
                tx = 1;
                if (en) begin
                    count_16 = 0;
                    next_state = START;
                end
            end
            START: begin
                if (baud_tick) begin
                    tx = 0;
                    if (count_16 == 16) begin
                        count_16 = 0;
                        next_state = DATA_BIT_0;
                    end
                    else begin
                        count_16 = count_16 + 1;
                    end
                end
            end
            DATA_BIT_0: begin
                if (baud_tick) begin
                    tx = data[0];
                    if (count_16 == 16) begin
                        count_16 = 0;
                        next_state = DATA_BIT_1;
                    end
                    else begin
                        count_16 = count_16 + 1;
                    end
                end
            end
            DATA_BIT_1: begin
                if (baud_tick) begin
                    tx = data[1];
                    if (count_16 == 16) begin
                        count_16 = 0;
                        next_state = DATA_BIT_2;
                    end
                    else begin
                        count_16 = count_16 + 1;
                    end
                end
            end
            DATA_BIT_2: begin
                if (baud_tick) begin
                    tx = data[2];
                    if (count_16 == 16) begin
                        count_16 = 0;
                        next_state = DATA_BIT_3;
                    end
                    else begin
                        count_16 = count_16 + 1;
                    end
                end
            end
            DATA_BIT_3: begin
                if (baud_tick) begin
                    tx = data[3];
                    if (count_16 == 16) begin
                        count_16 = 0;
                        next_state = DATA_BIT_4;
                    end
                    else begin
                        count_16 = count_16 + 1;
                    end
                end
            end
            DATA_BIT_4: begin
                if (baud_tick) begin
                    tx = data[4];
                    if (count_16 == 16) begin
                        count_16 = 0;
                        next_state = DATA_BIT_5;
                    end
                    else begin
                        count_16 = count_16 + 1;
                    end
                end
            end
            DATA_BIT_5: begin
                if (baud_tick) begin
                    tx = data[5];
                    if (count_16 == 16) begin
                        count_16 = 0;
                        next_state = DATA_BIT_6;
                    end
                    else begin
                        count_16 = count_16 + 1;
                    end
                end
            end
            DATA_BIT_6: begin
                if (baud_tick) begin
                    tx = data[6];
                    if (count_16 == 16) begin
                        count_16 = 0;
                        next_state = DATA_BIT_7;
                    end
                    else begin
                        count_16 = count_16 + 1;
                    end
                end
            end
            DATA_BIT_7: begin
                if (baud_tick) begin
                    tx = data[7];
                    if (count_16 == 16) begin
                        count_16 = 0;
                        next_state = STOP;
                    end
                    else begin
                        count_16 = count_16 + 1;
                    end
                end
            end
            STOP: begin
                if (baud_tick) begin
                    tx = 1;
                    if (count_16 == 16) begin
                        count_16 = 0;
                        next_state = IDLE;
                    end
                    else begin
                        count_16 = count_16 + 1;
                    end
                end
            end
            default: next_state = IDLE;
        endcase
    end

endmodule

tb/UART_Tx_tb.v
`timescale 1ns/1ns

module uart_tx_tb;
    
    reg clk,rst,en;
    reg baud_tick;
    reg [7:0] data;
    wire tx;

    uart_tx uut(clk,rst,en,baud_tick,data,tx);

    initial begin
        $dumpfile("./temp/UART_Tx_tb.vcd");
        $dumpvars(0,uart_tx_tb);
    end

    initial clk = 0;
    always #25 clk = ~clk;

    initial baud_tick = 0;
    always #3250 baud_tick = ~baud_tick;
    
    initial begin
        data = 8'b1011_0100;
        #50 rst = 1; en = 0;
        #50 rst = 0;
        #100 en = 1;
        #500000 en = 0;
        #1000000 en = 1;
        #500000 en = 0;
        #2000000 en = 1;
        #500000 en = 0;
        #1000000 $finish;
    end

endmodule

temp/UART_Tx_tb.vcd
$date
	Thu Nov 30 20:59:27 2023
$end
$version
	Icarus Verilog
$end
$timescale
	1ns
$end
$scope module uart_tx_tb $end
$var wire 1 ! tx $end
$var reg 1 " baud_tick $end
$var reg 1 # clk $end
$var reg 8 $ data [7:0] $end
$var reg 1 % en $end
$var reg 1 & rst $end
$scope module uut $end
$var wire 1 " baud_tick $end
$var wire 1 # clk $end
$var wire 8 ' data [7:0] $end
$var wire 1 % en $end
$var wire 1 & rst $end
$var reg 6 ( count_16 [5:0] $end
$var reg 4 ) current_state [3:0] $end
$var reg 4 * next_state [3:0] $end
$var reg 1 ! tx $end
$upscope $end
$upscope $end
$enddefinitions $end
#0
$dumpvars
b0 *
bx )
b0 (
b10110100 '
x&
x%
b10110100 $
0#
0"
x!
$end
#25
1!
b0 )
1#
#50
0#
0%
1&
#75
1#
#100
0#
0&
#125
1#
#150
0#
#175
1#
#200
b1 *
0#
1%
#225
b1 )
1#
#250
0#
#275
1#
#300
0#
#325
1#
#350
0#
#375
1#
#400
0#
#425
1#
#450
0#
#475
1#
#500
0#
#525
1#
#550
0#
#575
1#
#600
0#
#625
1#
#650
0#
#675
1#
#700
0#
#725
1#
#750
0#
#775
1#
#800
0#
#825
1#
#850
0#
#875
1#
#900
0#
#925
1#
#950
0#
#975
1#
#1000
0#
#1025
1#
#1050
0#
#1075
1#
#1100
0#
#1125
1#
#1150
0#
#1175
1#
#1200
0#
#1225
1#
#1250
0#
#1275
1#
#1300
0#
#1325
1#
#1350
0#
#1375
1#
#1400
0#
#1425
1#
#1450
0#
#1475
1#
#1500
0#
#1525
1#
#1550
0#
#1575
1#
#1600
0#
#1625
1#
#1650
0#
#1675
1#
#1700
0#
#1725
1#
#1750
0#
#1775
1#
#1800
0#
#1825
1#
#1850
0#
#1875
1#
#1900
0#
#1925
1#
#1950
0#
#1975
1#
#2000
0#
#2025
1#
#2050
0#
#2075
1#
#2100
0#
#2125
1#
#2150
0#
#2175
1#
#2200
0#
#2225
1#
#2250
0#
#2275
1#
#2300
0#
#2325
1#
#2350
0#
#2375
1#
#2400
0#
#2425
1#
#2450
0#
#2475
1#
#2500
0#
#2525
1#
#2550
0#
#2575
1#
#2600
0#
#2625
1#
#2650
0#
#2675
1#
#2700
0#
#2725
1#
#2750
0#
#2775
1#
#2800
0#
#2825
1#
#2850
0#
#2875
1#
#2900
0#
#2925
1#
#2950
0#
#2975
1#
#3000
0#
#3025
1#
#3050
0#
#3075
1#
#3100
0#
#3125
1#
#3150
0#
#3175
1#
#3200
0#
#3225
1#
#3250
b1 (
0!
0#
1"
#3275
1#
#3300
0#
#3325
1#
#3350
0#
#3375
1#
#3400
0#
#3425
1#
#3450
0#
#3475
1#
#3500
0#
#3525
1#
#3550
0#
#3575
1#
#3600
0#
#3625
1#
#3650
0#
#3675
1#
#3700
0#
#3725
1#
#3750
0#
#3775
1#
#3800
0#
#3825
1#
#3850
0#
#3875
1#
#3900
0#
#3925
1#
#3950
0#
#3975
1#
#4000
0#
#4025
1#
#4050
0#
#4075
1#
#4100
0#
#4125
1#
#4150
0#
#4175
1#
#4200
0#
#4225
1#
#4250
0#
#4275
1#
#4300
0#
#4325
1#
#4350
0#
#4375
1#
#4400
0#
#4425
1#
#4450
0#
#4475
1#
#4500
0#
#4525
1#
#4550
0#
#4575
1#
#4600
0#
#4625
1#
#4650
0#
#4675
1#
#4700
0#
#4725
1#
#4750
0#
#4775
1#
#4800
0#
#4825
1#
#4850
0#
#4875
1#
#4900
0#
#4925
1#
#4950
0#
#4975
1#
#5000
0#
#5025
1#
#5050
0#
#5075
1#
#5100
0#
#5125
1#
#5150
0#
#5175
1#
#5200
0#
#5225
1#
#5250
0#
#5275
1#
#5300
0#
#5325
1#
#5350
0#
#5375
1#
#5400
0#
#5425
1#
#5450
0#
#5475
1#
#5500
0#
#5525
1#
#5550
0#
#5575
1#
#5600
0#
#5625
1#
#5650
0#
#5675
1#
#5700
0#
#5725
1#
#5750
0#
#5775
1#
#5800
0#
#5825
1#
#5850
0#
#5875
1#
#5900
0#
#5925
1#
#5950
0#
#5975
1#
#6000
0#
#6025
1#
#6050
0#
#6075
1#
#6100
0#
#6125
1#
#6150
0#
#6175
1#
#6200
0#
#6225
1#
#6250
0#
#6275
1#
#6300
0#
#6325
1#
#6350
0#
#6375
1#
#6400
0#
#6425
1#
#6450
0#
#6475
1#
#6500
0#
0"
