src/UART_Baud_Rate.v
module uart_baud_rate (
    input clk,
    input rst,
    input [31:0] baud_division,
    output reg baud_tick
);
    
    reg [31:0] baud_count = 0;

    always @(posedge clk) begin
        if (rst) begin
            baud_count <= 0;
            baud_tick <= 0;
        end
        else begin
            if (baud_division != 0) begin
                if (baud_count == baud_division) begin
                    baud_count <= 0;
                    baud_tick <= 1;
                end
                else begin
                    baud_count <= baud_count + 1;
                    baud_tick <= 0;
                end
            end
            else begin
                baud_count <= 0;
                baud_tick <= 0;
            end
        end
    end

endmodule

tb/UART_Baud_Rate_tb.v
`timescale 1ns/1ns

module uart_baud_rate_tb;
    
    reg clk,rst;
    reg [31:0] baud_division;
    wire baud_tick;

    uart_baud_rate uut(clk,rst,baud_division,baud_tick);

    initial begin
        $dumpfile("./temp/UART_Baud_Rate_tb.vcd");
        $dumpvars(0,uart_baud_rate_tb);
    end

    initial clk = 0;
    always #25 clk = ~clk;
    
    initial begin
        baud_division = 130;
        #100 rst = 1;
        #500 rst = 0;
        #10000 $finish;
    end

endmodule

temp/UART_Baud_Rate_tb.vcd
$date
	Thu Nov 30 20:49:43 2023
$end
$version
	Icarus Verilog
$end
$timescale
	1ns
$end
$scope module uart_baud_rate_tb $end
$var wire 1 ! baud_tick $end
$var reg 32 " baud_division [31:0] $end
$var reg 1 # clk $end
$var reg 1 $ rst $end
$scope module uut $end
$var wire 32 % baud_division [31:0] $end
$var wire 1 # clk $end
$var wire 1 $ rst $end
$var reg 32 & baud_count [31:0] $end
$var reg 1 ! baud_tick $end
$upscope $end
$upscope $end
$enddefinitions $end
#0
$dumpvars
b0 &
b10000010 %
x$
0#
b10000010 "
x!
$end
#25
0!
b1 &
1#
#50
0#
#75
b10 &
1#
#100
0#
1$
#125
b0 &
1#
#150
0#
#175
1#
#200
0#
#225
1#
#250
0#
#275
1#
#300
0#
#325
1#
#350
0#
#375
1#
#400
0#
#425
1#
#450
0#
#475
1#
#500
0#
#525
1#
#550
0#
#575
1#
#600
0#
0$
#625
b1 &
1#
#650
0#
#675
b10 &
1#
#700
0#
#725
b11 &
1#
#750
0#
#775
b100 &
1#
#800
0#
#825
b101 &
1#
#850
0#
#875
b110 &
1#
#900
0#
#925
b111 &
1#
#950
0#
#975
b1000 &
1#
#1000
0#
#1025
b1001 &
1#
#1050
0#
#1075
b1010 &
1#
#1100
0#
#1125
b1011 &
1#
#1150
0#
#1175
b1100 &
1#
#1200
0#
#1225
b1101 &
1#
#1250
0#
#1275
b1110 &
1#
#1300
0#
#1325
b1111 &
1#
#1350
0#
#1375
b10000 &
1#
#1400
0#
#1425
b10001 &
1#
#1450
0#
#1475
b10010 &
1#
#1500
0#
#1525
b10011 &
1#
#1550
0#
#1575
b10100 &
1#
#1600
0#
#1625
b10101 &
1#
#1650
0#
#1675
b10110 &
1#
#1700
0#
#1725
b10111 &
1#
#1750
0#
#1775
b11000 &
1#
#1800
0#
#1825
b11001 &
1#
#1850
0#
#1875
b11010 &
1#
#1900
0#
#1925
b11011 &
1#
#1950
0#
#1975
b11100 &
1#
#2000
0#
#2025
b11101 &
1#
#2050
0#
#2075
b11110 &
1#
#2100
0#
#2125
b11111 &
1#
#2150
0#
#2175
b100000 &
1#
#2200
0#
#2225
b100001 &
1#
#2250
0#
#2275
b100010 &
1#
#2300
0#
#2325
b100011 &
1#
#2350
0#
#2375
b100100 &
1#
#2400
0#
#2425
b100101 &
1#
#2450
0#
#2475
b100110 &
1#
#2500
0#
#2525
b100111 &
1#
#2550
0#
#2575
b101000 &
1#
#2600
0#
#2625
b101001 &
1#
#2650
0#
#2675
b101010 &
1#
#2700
0#
#2725
b101011 &
1#
#2750
0#
#2775
b101100 &
1#
#2800
0#
#2825
b101101 &
1#
#2850
0#
#2875
b101110 &
1#
#2900
0#
#2925
b101111 &
1#
#2950
0#
#2975
b110000 &
1#
#3000
0#
#3025
b110001 &
1#
#3050
0#
#3075
b110010 &
1#
#3100
0#
#3125
b110011 &
1#
#3150
0#
#3175
b110100 &
1#
#3200
0#
#3225
b110101 &
1#
#3250
0#
#3275
b110110 &
1#
#3300
0#
#3325
b110111 &
1#
#3350
0#
#3375
b111000 &
1#
#3400
0#
#3425
b111001 &
1#
#3450
0#
#3475
b111010 &
1#
#3500
0#
#3525
b111011 &
1#
#3550
0#
#3575
b111100 &
1#
#3600
0#
#3625
b111101 &
1#
#3650
0#
#3675
b111110 &
1#
#3700
0#
#3725
b111111 &
1#
#3750
0#
#3775
b1000000 &
1#
#3800
0#
#3825
b1000001 &
1#
#3850
0#
#3875
b1000010 &
1#
#3900
0#
#3925
b1000011 &
1#
#3950
0#
#3975
b1000100 &
1#
#4000
0#
#4025
b1000101 &
1#
#4050
0#
#4075
b1000110 &
1#
#4100
0#
#4125
b1000111 &
1#
#4150
0#
#4175
b1001000 &
1#
#4200
0#
#4225
b1001001 &
1#
#4250
0#
#4275
b1001010 &
1#
#4300
0#
#4325
b1001011 &
1#
#4350
0#
#4375
b1001100 &
1#
#4400
0#
#4425
b1001101 &
1#
#4450
0#
#4475
b1001110 &
1#
#4500
0#
#4525
b1001111 &
1#
#4550
0#
#4575
b1010000 &
1#
#4600
0#
#4625
b1010001 &
1#
#4650
0#
#4675
b1010010 &
1#
#4700
0#
#4725
b1010011 &
1#
#4750
0#
#4775
b1010100 &
1#
#4800
0#
#4825
b1010101 &
1#
#4850
0#
#4875
b1010110 &
1#
#4900
0#
#4925
b1010111 &
1#
#4950
0#
#4975
b1011000 &
1#
#5000
0#
#5025
b1011001 &
1#
#5050
0#
#5075
b1011010 &
1#
#5100
0#
#5125
b1011011 &
1#
#5150
0#
#5175
b1011100 &
1#
#5200
0#
#5225
b1011101 &
1#
#5250
0#
#5275
b1011110 &
1#
#5300
0#
#5325
b1011111 &
1#
#5350
0#
#5375
b1100000 &
1#
#5400
0#
#5425
b1100001 &
1#
#5450
0#
#5475
b1100010 &
1#
#5500
0#
#5525
b1100011 &
1#
#5550
0#
#5575
b1100100 &
1#
#5600
0#
#5625
b1100101 &
1#
#5650
0#
#5675
b1100110 &
1#
#5700
0#
#5725
b1100111 &
1#
#5750
0#
#5775
b1101000 &
1#
#5800
0#
#5825
b1101001 &
1#
#5850
0#
#5875
b1101010 &
1#
#5900
0#
#5925
b1101011 &
1#
#5950
0#
#5975
b1101100 &
1#
#6000
0#
#6025
b1101101 &
1#
#6050
0#
#6075
b1101110 &
1#
#6100
0#
#6125
b1101111 &
1#
#6150
0#
#6175
b1110000 &
1#
#6200
0#
#6225
b1110001 &
1#
#6250
0#
#6275
b1110010 &
1#
#6300
0#
#6325
b1110011 &
1#
#6350
0#
#6375
b1110100 &
1#
#6400
0#
#6425
b1110101 &
1#
#6450
0#
#6475
b1110110 &
1#
#6500
0#
#6525
b1110111 &
1#
#6550
0#
#6575
b1111000 &
1#
#6600
0#
#6625
b1111001 &
1#
#6650
0#
#6675
b1111010 &
1#
#6700
0#
#6725
b1111011 &
1#
#6750
0#
#6775
b1111100 &
1#
#6800
0#
#6825
b1111101 &
1#
#6850
0#
#6875
b1111110 &
1#
#6900
0#
#6925
b1111111 &
1#
#6950
0#
#6975
b10000000 &
1#
#7000
0#
#7025
b10000001 &
1#
#7050
0#
#7075
b10000010 &
1#
#7100
0#
#7125
1!
b0 &
1#
#7150
0#
#7175
0!
b1 &
1#
#7200
0#
#7225
b10 &
1#
#7250
0#
#7275
b11 &
1#
#7300
0#
#7325
b100 &
1#
#7350
0#
#7375
b101 &
1#
#7400
0#
#7425
b110 &
1#
#7450
0#
#7475
b111 &
1#
#7500
0#
#7525
b1000 &
1#
#7550
0#
#7575
b1001 &
1#
#7600
0#
#7625
b1010 &
1#
#7650
0#
#7675
b1011 &
1#
#7700
0#
#7725
b1100 &
1#
#7750
0#
#7775
b1101 &
1#
#7800
0#
#7825
b1110 &
1#
#7850
0#
#7875
b1111 &
1#
#7900
0#
#7925
b10000 &
1#
#7950
0#
#7975
b10001 &
1#
#8000
0#
#8025
b10010 &
1#
#8050
0#
#8075
b10011 &
1#
#8100
0#
#8125
b10100 &
1#
#8150
0#
#8175
b10101 &
1#
#8200
0#
#8225
b10110 &
1#
#8250
0#
#8275
b10111 &
1#
#8300
0#
#8325
b11000 &
1#
#8350
0#
#8375
b11001 &
1#
#8400
0#
#8425
b11010 &
1#
#8450
0#
#8475
b11011 &
1#
#8500
0#
#8525
b11100 &
1#
#8550
0#
#8575
b11101 &
1#
#8600
0#
#8625
b11110 &
1#
#8650
0#
#8675
b11111 &
1#
#8700
0#
#8725
b100000 &
1#
#8750
0#
#8775
b100001 &
1#
#8800
0#
#8825
b100010 &
1#
#8850
0#
#8875
b100011 &
1#
#8900
0#
#8925
b100100 &
1#
#8950
0#
#8975
b100101 &
1#
#9000
0#
#9025
b100110 &
1#
#9050
0#
#9075
b100111 &
1#
#9100
0#
#9125
b101000 &
1#
#9150
0#
#9175
b101001 &
1#
#9200
0#
#9225
b101010 &
1#
#9250
0#
#9275
b101011 &
1#
#9300
0#
#9325
b101100 &
1#
#9350
0#
#9375
b101101 &
1#
#9400
0#
#9425
b101110 &
1#
#9450
0#
#9475
b101111 &
1#
#9500
0#
#9525
b110000 &
1#
#9550
0#
#9575
b110001 &
1#
#9600
0#
#9625
b110010 &
1#
#9650
0#
#9675
b110011 &
1#
#9700
0#
#9725
b110100 &
1#
#9750
0#
#9775
b110101 &
1#
#9800
0#
#9825
b110110 &
1#
#9850
0#
#9875
b110111 &
1#
#9900
0#
#9925
b111000 &
1#
#9950
0#
#9975
b111001 &
1#
#10000
0#
#10025
b111010 &
1#
#10050
0#
#10075
b111011 &
1#
#10100
0#
#10125
b111100 &
1#
#10150
0#
#10175
b111101 &
1#
#10200
0#
#10225
b111110 &
1#
#10250
0#
#10275
b111111 &
1#
#10300
0#
#10325
b1000000 &
1#
#10350
0#
#10375
b1000001 &
1#
#10400
0#
#10425
b1000010 &
1#
#10450
0#
#10475
b1000011 &
1#
#10500
0#
#10525
b1000100 &
1#
#10550
0#
#10575
b1000101 &
1#
